{"BaseModel.5b1fa0a0-d692-4630-88cd-d156158d87b0": {"id": "5b1fa0a0-d692-4630-88cd-d156158d87b0", "created_at": "2024-03-10T17:41:03.912198", "updated_at": "2024-03-10T17:41:03.912208", "name": "My_First_Model", "my_number": 89, "__class__": "BaseModel"}, "BaseModel.7b510cfd-b7a9-4506-beef-c4c667983e9b": {"id": "7b510cfd-b7a9-4506-beef-c4c667983e9b", "created_at": "2024-03-10T17:52:01.641533", "updated_at": "2024-03-10T17:52:01.641538", "name": "My_First_Model", "my_number": 89, "__class__": "BaseModel"}, "BaseModel.a4a46b07-e599-440a-afb7-3d28226bf505": {"id": "a4a46b07-e599-440a-afb7-3d28226bf505", "created_at": "2024-03-10T17:55:17.797350", "updated_at": "2024-03-10T17:55:17.797355", "name": "My_First_Model", "my_number": 89, "__class__": "BaseModel"}}